{
  "__inputs": [
    {
      "name": "DS_PROMETHEUS",
      "label": "Prometheus",
      "description": "Prometheus datasource scraping miniboxd /metrics",
      "type": "datasource",
      "pluginId": "prometheus",
      "pluginName": "Prometheus"
    }
  ],
  "__requires": [
    {
      "type": "grafana",
      "id": "grafana",
      "name": "Grafana",
      "version": "10.0.0"
    },
    {
      "type": "datasource",
      "id": "prometheus",
      "name": "Prometheus",
      "version": "1.0.0"
    },
    {
      "type": "panel",
      "id": "stat",
      "name": "Stat",
      "version": ""
    },
    {
      "type": "panel",
      "id": "timeseries",
      "name": "Time series",
      "version": ""
    }
  ],
  "annotations": {
    "list": []
  },
  "description": "miniboxd container runtime — ops counters, durations, active containers",
  "editable": true,
  "fiscalYearStartMonth": 0,
  "graphTooltip": 1,
  "id": null,
  "links": [],
  "panels": [
    {
      "datasource": { "type": "prometheus", "uid": "${DS_PROMETHEUS}" },
      "fieldConfig": {
        "defaults": {
          "color": { "mode": "thresholds" },
          "mappings": [],
          "thresholds": {
            "mode": "absolute",
            "steps": [
              { "color": "green", "value": null },
              { "color": "yellow", "value": 10 },
              { "color": "red", "value": 50 }
            ]
          },
          "unit": "short"
        },
        "overrides": []
      },
      "gridPos": { "h": 4, "w": 4, "x": 0, "y": 0 },
      "id": 1,
      "options": {
        "colorMode": "value",
        "graphMode": "none",
        "justifyMode": "center",
        "orientation": "auto",
        "reduceOptions": { "calcs": ["lastNotNull"], "fields": "", "values": false },
        "textMode": "auto"
      },
      "title": "Active Containers",
      "type": "stat",
      "targets": [
        {
          "datasource": { "type": "prometheus", "uid": "${DS_PROMETHEUS}" },
          "expr": "minibox_active_containers",
          "legendFormat": "active",
          "refId": "A"
        }
      ]
    },
    {
      "datasource": { "type": "prometheus", "uid": "${DS_PROMETHEUS}" },
      "fieldConfig": {
        "defaults": {
          "color": { "mode": "palette-classic" },
          "custom": {
            "axisCenteredZero": false,
            "axisColorMode": "text",
            "axisLabel": "ops/s",
            "axisPlacement": "auto",
            "barAlignment": 0,
            "drawStyle": "line",
            "fillOpacity": 10,
            "gradientMode": "none",
            "hideFrom": { "legend": false, "tooltip": false, "viz": false },
            "lineInterpolation": "linear",
            "lineWidth": 1,
            "pointSize": 5,
            "scaleDistribution": { "type": "linear" },
            "showPoints": "never",
            "spanNulls": false,
            "stacking": { "group": "A", "mode": "none" },
            "thresholdsStyle": { "mode": "off" }
          },
          "mappings": [],
          "thresholds": { "mode": "absolute", "steps": [{ "color": "green", "value": null }] },
          "unit": "ops"
        },
        "overrides": []
      },
      "gridPos": { "h": 8, "w": 10, "x": 4, "y": 0 },
      "id": 2,
      "options": {
        "legend": { "calcs": ["mean", "max"], "displayMode": "table", "placement": "bottom" },
        "tooltip": { "mode": "multi", "sort": "none" }
      },
      "title": "Op Rate (ops/s)",
      "type": "timeseries",
      "targets": [
        {
          "datasource": { "type": "prometheus", "uid": "${DS_PROMETHEUS}" },
          "expr": "sum by (op) (rate(minibox_container_ops_total{status=\"ok\"}[2m]))",
          "legendFormat": "{{op}} ok",
          "refId": "A"
        }
      ]
    },
    {
      "datasource": { "type": "prometheus", "uid": "${DS_PROMETHEUS}" },
      "fieldConfig": {
        "defaults": {
          "color": { "mode": "palette-classic" },
          "custom": {
            "drawStyle": "line",
            "fillOpacity": 10,
            "lineWidth": 1,
            "showPoints": "never",
            "spanNulls": false
          },
          "unit": "percentunit"
        },
        "overrides": []
      },
      "gridPos": { "h": 8, "w": 10, "x": 14, "y": 0 },
      "id": 3,
      "options": {
        "legend": { "calcs": ["mean"], "displayMode": "table", "placement": "bottom" },
        "tooltip": { "mode": "multi", "sort": "none" }
      },
      "title": "Error Rate by Op",
      "type": "timeseries",
      "targets": [
        {
          "datasource": { "type": "prometheus", "uid": "${DS_PROMETHEUS}" },
          "expr": "sum by (op) (rate(minibox_container_ops_total{status=\"error\"}[2m])) / sum by (op) (rate(minibox_container_ops_total[2m]))",
          "legendFormat": "{{op}}",
          "refId": "A"
        }
      ]
    },
    {
      "datasource": { "type": "prometheus", "uid": "${DS_PROMETHEUS}" },
      "fieldConfig": {
        "defaults": {
          "color": { "mode": "palette-classic" },
          "custom": {
            "drawStyle": "line",
            "fillOpacity": 10,
            "lineWidth": 1,
            "showPoints": "never",
            "spanNulls": false
          },
          "unit": "s"
        },
        "overrides": []
      },
      "gridPos": { "h": 8, "w": 24, "x": 0, "y": 8 },
      "id": 4,
      "options": {
        "legend": { "calcs": ["mean", "max"], "displayMode": "table", "placement": "bottom" },
        "tooltip": { "mode": "multi", "sort": "none" }
      },
      "title": "Op Duration p95 (seconds)",
      "type": "timeseries",
      "targets": [
        {
          "datasource": { "type": "prometheus", "uid": "${DS_PROMETHEUS}" },
          "expr": "histogram_quantile(0.95, sum by (op, le) (rate(minibox_container_op_duration_seconds_bucket[2m])))",
          "legendFormat": "{{op}} p95",
          "refId": "A"
        },
        {
          "datasource": { "type": "prometheus", "uid": "${DS_PROMETHEUS}" },
          "expr": "histogram_quantile(0.50, sum by (op, le) (rate(minibox_container_op_duration_seconds_bucket[2m])))",
          "legendFormat": "{{op}} p50",
          "refId": "B"
        }
      ]
    }
  ],
  "refresh": "10s",
  "schemaVersion": 38,
  "tags": ["minibox", "containers"],
  "templating": {
    "list": [
      {
        "current": {},
        "hide": 0,
        "includeAll": false,
        "multi": false,
        "name": "DS_PROMETHEUS",
        "options": [],
        "query": "prometheus",
        "refresh": 1,
        "type": "datasource",
        "label": "Prometheus Datasource"
      }
    ]
  },
  "time": { "from": "now-1h", "to": "now" },
  "timepicker": {},
  "timezone": "browser",
  "title": "Minibox Container Runtime",
  "uid": "minibox-runtime-v1",
  "version": 1,
  "weekStart": ""
}
